pylexers/__init__.py
pylexers/BaseLexer/__init__.py
pylexers/DFALexer/DFA.py
pylexers/DFALexer/__init__.py
pylexers/DerivativeLexer/__init__.py
pylexers/NFALexer/NFA.py
pylexers/NFALexer/__init__.py
pylexers/NFALexer/nfa_from_re.py
pylexers/RegularExpressions/BaseRegularExpressions.py
pylexers/RegularExpressions/__init__.py
pylexers/SymbolTable/__init__.py
pylexers-3.1.dist-info/LICENSE
pylexers-3.1.dist-info/METADATA
pylexers-3.1.dist-info/WHEEL
pylexers-3.1.dist-info/top_level.txt
pylexers-3.1.dist-info/RECORD
